alchemy/__init__.py
alchemy/utils.py
alchemy/dataset/__init__.py
alchemy/dataset/data_backend.py
alchemy/dataset/filelist.py
alchemy/dataset/lmdb.py
alchemy/diff_render/__init__.py
alchemy/diff_render/sh_shading.py
alchemy/diff_render/test_shading.py
alchemy/onnx_pytorch/__init__.py
alchemy/onnx_pytorch/onnx_to_pytorch.py
alchemy/scaffold/__init__.py
alchemy/scaffold/callback.py
alchemy/scaffold/logger.py
alchemy_xiao_mcg-0.2.2.dist-info/METADATA
alchemy_xiao_mcg-0.2.2.dist-info/WHEEL
alchemy_xiao_mcg-0.2.2.dist-info/top_level.txt
alchemy_xiao_mcg-0.2.2.dist-info/RECORD
