Metadata-Version: 2.1
Name: alchemy-xiao-mcg
Version: 0.2.2
Summary: A set of wrapped classes based on Pytorch-lightning for fast development of deep learning projects.
Home-page: https://pableetox@dev.azure.com/pableetox/Prototypes/_git/alchemy
Author: Xiao Li
Author-email: xili11@microsoft.com
License: UNKNOWN
Platform: UNKNOWN
Classifier: Programming Language :: Python :: 3
Requires-Python: >=3.5
